.gitignore
CHANGES.txt
LICENCE.txt
README.md
setup.py
mrwolfe/TODO
mrwolfe/__init__.py
mrwolfe/admin.py
mrwolfe/mailutils.py
mrwolfe/notification.py
mrwolfe/search_indexes.py
mrwolfe/settings.py
mrwolfe/urls.py
mrwolfe/utils.py
mrwolfe.egg-info/PKG-INFO
mrwolfe.egg-info/SOURCES.txt
mrwolfe.egg-info/dependency_links.txt
mrwolfe.egg-info/not-zip-safe
mrwolfe.egg-info/requires.txt
mrwolfe.egg-info/top_level.txt
mrwolfe/docs/install.md
mrwolfe/docs/intro.md
mrwolfe/docs/issue_detail.png
mrwolfe/docs/issues_overview.png
mrwolfe/docs/openid.md
mrwolfe/docs/settings.md
mrwolfe/docs/skin.md
mrwolfe/docs/usage.md
mrwolfe/docs/wiki.md
mrwolfe/forms/__init__.py
mrwolfe/forms/base.py
mrwolfe/forms/comment.py
mrwolfe/forms/contact.py
mrwolfe/forms/issue.py
mrwolfe/forms/login.py
mrwolfe/forms/mailqueue.py
mrwolfe/forms/operator.py
mrwolfe/forms/rule.py
mrwolfe/forms/search.py
mrwolfe/forms/service.py
mrwolfe/forms/setting.py
mrwolfe/forms/sla.py
mrwolfe/forms/status.py
mrwolfe/management/__init__.py
mrwolfe/management/commands/__init__.py
mrwolfe/management/commands/readmail.py
mrwolfe/models/__init__.py
mrwolfe/models/attachment.py
mrwolfe/models/comment.py
mrwolfe/models/contact.py
mrwolfe/models/issue.py
mrwolfe/models/mailqueue.py
mrwolfe/models/operator.py
mrwolfe/models/rule.py
mrwolfe/models/service.py
mrwolfe/models/setting.py
mrwolfe/models/signal_processors.py
mrwolfe/models/sla.py
mrwolfe/models/status.py
mrwolfe/models/user.py
mrwolfe/staticsources/css/mrwolfe.css
mrwolfe/staticsources/img/loading.gif
mrwolfe/staticsources/js/mrwolfe.js
mrwolfe/templates/500.html
mrwolfe/templates/addform.html
mrwolfe/templates/admin.html
mrwolfe/templates/base.html
mrwolfe/templates/confirm_delete.html
mrwolfe/templates/create_base_modal.html
mrwolfe/templates/create_issue.html
mrwolfe/templates/create_sla.html
mrwolfe/templates/create_status.html
mrwolfe/templates/edit_issue.html
mrwolfe/templates/edit_sla.html
mrwolfe/templates/editform.html
mrwolfe/templates/help.html
mrwolfe/templates/index.html
mrwolfe/templates/login.html
mrwolfe/templates/view_issue.html
mrwolfe/templates/view_sla.html
mrwolfe/templates/controls/assignee_control.html
