Metadata-Version: 1.1
Name: mrwolfe
Version: 1.2.0
Summary: Django Issue tracker & support system
Home-page: https://github.com/wyldebeast-wunderliebe/mrwolfe/
Author: D.A.Dokter
Author-email: dokter@w20e.com
License: beer-ware
Keywords: django issue tracker support
Platform: UNKNOWN
Classifier: Development Status :: 4 - Beta
Classifier: Framework :: Django
Classifier: Intended Audience :: Developers
Classifier: License :: Freely Distributable
Classifier: Programming Language :: Python
Classifier: Topic :: Internet :: WWW/HTTP :: Site Management
Classifier: Topic :: Software Development :: Libraries :: Application Frameworks
